Workbook

Sheet Summary
A1: AR Workbench – Requirements Retest Report (Handoff v1.1)
A3: Requirement source | B3: AR_Workbench_Developer_Handoff_Requirements_v1.1.docx — Part A (session decisions), Part B (FR-xx), Part C (mockup rules), Part E (NFR)
A4: Application | B4: https://www.lrnanalytics.com/ARWBTest/ (Test) – build index-CUr4SgQD.js – lab Inhealth_DTR
A5: Data | B5: Master file load 18 Oct 2026 (sync 9:01 PM) – 84,494 claims / 151,984 CPT lines
A6: Retest date | B6: 19 Oct 2026 (baseline run 15 Oct 2026)
A7: Roles tested | B7: System Administrator, AR Agent (ARAgent1), QA Reviewer (QA1), Team Lead, RCM Manager, Clinic Viewer (Insight Family Practice), Client Viewer (AccountManager)
A8: Method | B8: API reconciliation of all claims + UI walkthrough + end-to-end role workflows on 10 fresh test claims (user-approved changes to Test data)
A10: Status | B10: Part A Test Cases | C10: Part B FR Traceability | D10: Part C Mockup Rules | E10: Part E NFR | F10: Role Workflow Retest | G10: Total
A11: Pass | B11: =COUNTIF('Part A Test Cases'!$J$2:$J$69,$A11) -> 57 | C11: =COUNTIF('Part B FR Traceability'!$D$2:$D$137,$A11) -> 105 | D11: =COUNTIF('Part C Mockup Rules'!$D$2:$D$23,$A11) -> 21 | E11: =COUNTIF('Part E NFR'!$C$2:$C$10,$A11) -> 3 | F11: =COUNTIF('Role Workflow Retest'!$I$2:$I$32,$A11) -> 28 | G11: =SUM(B11:F11) -> 214
A12: Fail | B12: =COUNTIF('Part A Test Cases'!$J$2:$J$69,$A12) -> 1 | C12: =COUNTIF('Part B FR Traceability'!$D$2:$D$137,$A12) -> 6 | D12: =COUNTIF('Part C Mockup Rules'!$D$2:$D$23,$A12) -> 0 | E12: =COUNTIF('Part E NFR'!$C$2:$C$10,$A12) -> 0 | F12: =COUNTIF('Role Workflow Retest'!$I$2:$I$32,$A12) -> 0 | G12: =SUM(B12:F12) -> 7
A13: Partial | B13: =COUNTIF('Part A Test Cases'!$J$2:$J$69,$A13) -> 3 | C13: =COUNTIF('Part B FR Traceability'!$D$2:$D$137,$A13) -> 9 | D13: =COUNTIF('Part C Mockup Rules'!$D$2:$D$23,$A13) -> 1 | E13: =COUNTIF('Part E NFR'!$C$2:$C$10,$A13) -> 0 | F13: =COUNTIF('Role Workflow Retest'!$I$2:$I$32,$A13) -> 3 | G13: =SUM(B13:F13) -> 16
A14: Blocked | B14: =COUNTIF('Part A Test Cases'!$J$2:$J$69,$A14) -> 2 | C14: =COUNTIF('Part B FR Traceability'!$D$2:$D$137,$A14) -> 1 | D14: =COUNTIF('Part C Mockup Rules'!$D$2:$D$23,$A14) -> 0 | E14: =COUNTIF('Part E NFR'!$C$2:$C$10,$A14) -> 0 | F14: =COUNTIF('Role Workflow Retest'!$I$2:$I$32,$A14) -> 0 | G14: =SUM(B14:F14) -> 3
A15: Not Executed | B15: =COUNTIF('Part A Test Cases'!$J$2:$J$69,$A15) -> 2 | C15: =COUNTIF('Part B FR Traceability'!$D$2:$D$137,$A15) -> 9 | D15: =COUNTIF('Part C Mockup Rules'!$D$2:$D$23,$A15) -> 0 | E15: =COUNTIF('Part E NFR'!$C$2:$C$10,$A15) -> 5 | F15: =COUNTIF('Role Workflow Retest'!$I$2:$I$32,$A15) -> 0 | G15: =SUM(B15:F15) -> 16
A16: Not Retested | B16: =COUNTIF('Part A Test Cases'!$J$2:$J$69,$A16) -> 2 | C16: =COUNTIF('Part B FR Traceability'!$D$2:$D$137,$A16) -> 5 | D16: =COUNTIF('Part C Mockup Rules'!$D$2:$D$23,$A16) -> 0 | E16: =COUNTIF('Part E NFR'!$C$2:$C$10,$A16) -> 0 | F16: =COUNTIF('Role Workflow Retest'!$I$2:$I$32,$A16) -> 0 | G16: =SUM(B16:F16) -> 7
A17: N/A (Phase 2) | B17: =COUNTIF('Part A Test Cases'!$J$2:$J$69,$A17) -> 1 | C17: =COUNTIF('Part B FR Traceability'!$D$2:$D$137,$A17) -> 0 | D17: =COUNTIF('Part C Mockup Rules'!$D$2:$D$23,$A17) -> 0 | E17: =COUNTIF('Part E NFR'!$C$2:$C$10,$A17) -> 0 | F17: =COUNTIF('Role Workflow Retest'!$I$2:$I$32,$A17) -> 0 | G17: =SUM(B17:F17) -> 1
A18: N/A (Open item) | B18: =COUNTIF('Part A Test Cases'!$J$2:$J$69,$A18) -> 0 | C18: =COUNTIF('Part B FR Traceability'!$D$2:$D$137,$A18) -> 1 | D18: =COUNTIF('Part C Mockup Rules'!$D$2:$D$23,$A18) -> 0 | E18: =COUNTIF('Part E NFR'!$C$2:$C$10,$A18) -> 0 | F18: =COUNTIF('Role Workflow Retest'!$I$2:$I$32,$A18) -> 0 | G18: =SUM(B18:F18) -> 1
A19: N/A | B19: =COUNTIF('Part A Test Cases'!$J$2:$J$69,$A19) -> 0 | C19: =COUNTIF('Part B FR Traceability'!$D$2:$D$137,$A19) -> 0 | D19: =COUNTIF('Part C Mockup Rules'!$D$2:$D$23,$A19) -> 0 | E19: =COUNTIF('Part E NFR'!$C$2:$C$10,$A19) -> 1 | F19: =COUNTIF('Role Workflow Retest'!$I$2:$I$32,$A19) -> 0 | G19: =SUM(B19:F19) -> 1
A20: Total | B20: =SUM(B11:B19) -> 68 | C20: =SUM(C11:C19) -> 136 | D20: =SUM(D11:D19) -> 22 | E20: =SUM(E11:E19) -> 9 | F20: =SUM(F11:F19) -> 31 | G20: =SUM(G11:G19) -> 266
A21: Pass rate (of executed) | B21: =IFERROR(B11/(B11+B12+B13),0) -> 0.93442623 | C21: =IFERROR(C11/(C11+C12+C13),0) -> 0.875 | D21: =IFERROR(D11/(D11+D12+D13),0) -> 0.95454545 | E21: =IFERROR(E11/(E11+E12+E13),0) -> 1 | F21: =IFERROR(F11/(F11+F12+F13),0) -> 0.90322581 | G21: =IFERROR(G11/(G11+G12+G13),0) -> 0.90295359
A22: Executed = Pass + Fail + Partial
A24: Part A trend (68 cases)
A25: Status | B25: 15 Oct | C25: 19 Oct | D25: Change
A26: Pass | B26: =COUNTIF('Part A Test Cases'!$K$2:$K$69,A26) -> 34 | C26: =COUNTIF('Part A Test Cases'!$J$2:$J$69,A26) -> 57 | D26: =C26-B26 -> 23
A27: Fail | B27: =COUNTIF('Part A Test Cases'!$K$2:$K$69,A27) -> 12 | C27: =COUNTIF('Part A Test Cases'!$J$2:$J$69,A27) -> 1 | D27: =C27-B27 -> -11
A28: Partial | B28: =COUNTIF('Part A Test Cases'!$K$2:$K$69,A28) -> 14 | C28: =COUNTIF('Part A Test Cases'!$J$2:$J$69,A28) -> 3 | D28: =C28-B28 -> -11
A29: Blocked | B29: =COUNTIF('Part A Test Cases'!$K$2:$K$69,A29) -> 3 | C29: =COUNTIF('Part A Test Cases'!$J$2:$J$69,A29) -> 2 | D29: =C29-B29 -> -1
A30: Not Executed | B30: =COUNTIF('Part A Test Cases'!$K$2:$K$69,A30) -> 4 | C30: =COUNTIF('Part A Test Cases'!$J$2:$J$69,A30) -> 2 | D30: =C30-B30 -> -2
A31: Not Retested | B31: =COUNTIF('Part A Test Cases'!$K$2:$K$69,A31) -> 0 | C31: =COUNTIF('Part A Test Cases'!$J$2:$J$69,A31) -> 2 | D31: =C31-B31 -> 2
A32: N/A (Phase 2) | B32: =COUNTIF('Part A Test Cases'!$K$2:$K$69,A32) -> 1 | C32: =COUNTIF('Part A Test Cases'!$J$2:$J$69,A32) -> 1 | D32: =C32-B32 -> 0
A35: Defect retest
A36: Retest status | B36: Count
A37: Fixed | B37: =COUNTIF('Defect Log'!$G$2:$G$32,A37) -> 20
A38: Partially fixed | B38: =COUNTIF('Defect Log'!$G$2:$G$32,A38) -> 0
A39: Open | B39: =COUNTIF('Defect Log'!$G$2:$G$32,A39) -> 0
A40: New | B40: =COUNTIF('Defect Log'!$G$2:$G$32,A40) -> 10
A41: Withdrawn | B41: =COUNTIF('Defect Log'!$G$2:$G$32,A41) -> 1
A43: Key findings
A44: 1. All 20 defects from 15 Oct are fixed, incl. the Critical client internal-note leak (DEF-15), QA data exposure (DEF-16), agent write-off posting (DEF-17), Clinic Viewer CIP response (DEF-18), Document Vault & categorised follow-up attachments (DEF-13/14) and Manager NC-list access (DEF-08). DEF-20 (auto-adjust balance) is fixed in the UI and DEF-07 confirmed (284 claims classify correctly; 284 only missing from the Denial Code Master — OBS-28).
A45: 2. Financial fields now work: Revenue Expectation populated for 84,481 claims and Potential Recovery formula correct on 141/141 sampled claims; Recovered Amount is payments-only.
A46: 3. Weekly re-sync rules verified on real syncs: unposted adjustments / write-offs flagged and returned to Auto Adjustments with agent and manager notifications; claims closing on sync are closed and audited.
A47: 4. New defects (v1.1 scope): Recovery Status wrong for Patient AR claims (DEF-22); Control Plan / SLA dashboard widgets, Work Queue 'More filters', client line-item export not built (DEF-23/24/29); plus 6 Low items. DEF-21 (Revenue Expectation line inclusion) withdrawn — RSKP confirmed RE covers collectible Denied / No Response lines only.
A48: 5. End-to-end role workflows pass for all 7 roles (31 steps: 28 Pass, 3 Partial, 0 Fail).
A49: 6. Still not executable: New-Denials re-sync path, 45-day re-follow-up (first eligible 21 Nov), RARC handling (no data), and infra/HIPAA controls.

Sheet Part A Test Cases
A1: Test Case ID | B1: Module | C1: Requirement Ref | D1: Priority | E1: Test Scenario | F1: Test Data / Pre-conditions | G1: Test Steps | H1: Expected Result | I1: Actual Result (19 Oct retest) | J1: Status (19 Oct) | K1: Status (15 Oct) | L1: Defect / Obs Ref
A2: TC-001 | B2: Data Sync & Grain | C2: §2.1 / Feature #1 | D2: High | E2: Full claim-level master file is synced for the lab | F2: Lab Inhealth_DTR; Data Processing run #3 (R20261005INH3267 ... 09.22–09.28.2026.csv) | G2: 1. Open Data Processing. 2. Review Run history and source counters. 3. Reconcile claim count to queue totals via API. | H2: Every claim in the claim-level master file is loaded (not only insight-linked claims); line-level file also read. | I2: Master File Load from SharePoint + Data Processing present. Latest load 18 Oct 2026 3:59 PM, synced 9:01 PM; 84,494 claims / 151,984 CPT lines; 'Master File Loaded' now populated. | J2: Pass | K2: Pass
A3: TC-002 | B3: Data Sync & Grain | C3: §2.1 | D3: Medium | E3: Sync cadence is weekly and aligned with master refresh | F3: Run history; Nightly Queue Snapshots | G3: 1. Review run history dates. 2. Review nightly snapshot table. | H3: Weekly sync runs recorded; nightly recalculation of aging / TFL / re-follow-up. | I3: Weekly loads with run log; nightly queue snapshots through 19 Oct 2026. | J3: Pass | K3: Pass
A4: TC-003 | B4: Data Sync & Grain | C4: §2.1, §3 | D4: High | E4: Every list, queue and count is at claim grain; each claim sits in exactly one financial queue | F4: All 84,074 claims pulled via claims API (read-only) | G4: 1. Pull all claims. 2. Check unique claim keys. 3. Sum queue/sub-queue counts. | H4: Unique claim count = total; each claim in exactly one queue. | I4: 84,494 claims pulled; 84,494 unique keys; queue counts sum to total. | J4: Pass | K4: Pass
A5: TC-004 | B5: Denial Insights | C5: §2.2 | D5: High | E5: Dashboard 'Latest Denial Analysis Report insights' shows the CURRENT week's insights | F5: Current week (Oct 14, 2026) has 1 uploaded Key Observation (CO-216) | G5: 1. Open Dashboard. 2. Compare insight list with Data Processing > Current week. | H5: Dashboard shows the same current-week insights as Data Processing, with description populated. | I5: Dashboard now shows the current week's uploaded Key Observations (week of 14 Oct) with description 'BASED ON THE FINDINGS OF A REVIEW ORGANIZATION'. | J5: Pass | K5: Fail | L5: DEF-01, DEF-02 fixed
A6: TC-005 | B6: Denial Insights | C6: §2.2 | D6: Medium | E6: Data Processing shows current + previous week insights, unresolved items only | F6: Data Processing > Denial Analysis Report | G6: 1. Open Current week tab. 2. Open Previous week tab. 3. Check 'still open' counts. | H6: Two tabs (current & previous); counts reflect only unresolved / unassigned items. | I6: Current week (14 Oct) and Previous week (05 Oct) tabs; counts are open + unassigned. | J6: Pass | K6: Partial
A7: TC-006 | B7: Denial Insights | C7: §2.2 | D7: High | E7: Clicking an insight routes to the filtered claim set in the Work Queue for bulk assignment | F7: Insight CO-216 (Still open 1,699) | G7: 1. Data Processing > Current week. 2. Click 'Route to Work Queue' on CO-216. | H7: Work Queue opens filtered to the insight's unassigned open claims; count equals insight's open count. | I7: Not re-run (unchanged route). 15-Oct result: filter chip CO-216 + Unassigned + Open; 1,700 vs 1,699. | J7: Not Retested | K7: Partial | L7: OBS-02
A8: TC-007 | B8: Denial Insights | C8: §2.2 | D8: Medium | E8: Insight counts cover all payers; Highest-impact payer is informational only | F8: Insight CO-216 | G8: 1. Compare # of denials vs. Ins. # of denials for top payer. | H8: Count and balance cover all payers; top payer is not used as a filter. | I8: Not re-run. 15-Oct: counts across all payers; top payer informational. | J8: Not Retested | K8: Pass
A9: TC-008 | B9: Denial Insights | C9: §2.2, AT-7, Feature #3 | D9: High | E9: Assigned claims are deducted from insight outstanding count/balance | F9: CO-216: 2,051 total; 10 already assigned | G9: 1. Read insight 'Still open'. 2. Independently recompute open, unassigned claims with primary denial 216. | H9: Insight shows only the unassigned remainder. | I9: Insight 216 'still open' 2,219 / $773,349.77 = independent recompute of open, unassigned claims with primary 216 (2,219 / $773,349.77). Note: 'Still Open' (2,219) exceeds the uploaded '# of Denials' (2,051) — see OBS-25. | J9: Pass | K9: Pass | L9: OBS-25
A10: TC-009 | B10: Claim Detail | C10: §2.3 | D10: Medium | E10: Denial Info shows the claim's primary denial (code, description, category, classification) | F10: Claim 19448764 (curated denial 'CO11, CO252') | G10: 1. Open claim. 2. Open Denial Info tab. | H10: Primary code, description, category and classification populated. | I10: Claim 19448764 Denial Info: Primary 11 (as received CO11), Reason 'Diagnosis inconsistent with procedure', All Denial Codes '11, 252', Line-Level Codes listed separately. | J10: Pass | K10: Partial | L10: DEF-03 fixed
A11: TC-010 | B11: Claim Detail | C11: §2.3, Feature #4 | D11: Medium | E11: CPT Line-Level Detail has an expand control per CPT showing line-level denial code (prefix retained), description, classification | F11: Claim 19448764 (7 CPT lines) | G11: 1. Open CPT / Line Detail tab. 2. Look for expand control on each CPT. | H11: Each CPT row expandable; reveals line denial code with original prefix, description and classification. | I11: Per-CPT expand control ('Expand denials for CPT 87481'); expanded row shows CO11 · date · description · category; prefix retained for display. | J11: Pass | K11: Partial | L11: DEF-04 fixed
A12: TC-011 | B12: Claim Detail | C12: §2.3 | D12: Medium | E12: Line-level data does not drive queue placement | F12: Claim 19448764: lines Denied CO11/CO252 + 5 Partially Adjusted lines | G12: 1. Compare line statuses with claim AR Queue. | H12: Queue derived from claim-level primary denial only. | I12: Queue still from claim-level primary (19448764 Denied · Possible Collectible). | J12: Pass | K12: Pass
A13: TC-012 | B13: AR Queue Logic | C13: §3.1, AT-1 | D13: High | E13: Closed – Fully Paid: Ins Bal = 0 and Pt Bal = 0; not fed to work queue | F13: All claims (API) | G13: 1. Check every Closed claim balance. 2. Check no zero-balance claim sits outside Closed. 3. Check queue is non-priority. | H13: All Closed – Fully Paid claims have zero balances; not in active work-queue feed. | I13: 43,003 Closed – Fully Paid, all zero balance; 0 closed with balance. 7 zero-balance claims sit in Status Change Verification pending manager review. | J13: Pass | K13: Pass | L13: OBS-20
A14: TC-013 | B14: AR Queue Logic | C14: §3.1 | D14: High | E14: Closed – Fully Adjusted: fully adjusted, no balance | F14: All claims (API) | G14: 1. Check balances of Closed – Fully Adjusted claims. | H14: Zero insurance and patient balance. | I14: 21,408 Closed – Fully Adjusted, all zero balance. | J14: Pass | K14: Pass
A15: TC-014 | B15: AR Queue Logic | C15: §3.1, AT-2 | D15: High | E15: Non-Responder: Ins Bal > 0, no payment/denial/adjustment; auto-fed to work queue | F15: All claims (API) | G15: 1. Check Non-Responder claims for denial codes and balance. 2. Check priority flag. | H15: All have Ins Bal > 0 and no denial; queue is auto-fed. | I15: 1,715 Non-Responder; 0 with denial; all Ins Bal > 0. | J15: Pass | K15: Pass
A16: TC-015 | B16: AR Queue Logic | C16: §3.1, §4.1 | D16: High | E16: Denied – Possible Collectible: Ins Bal > 0, primary denial NOT on NC List | F16: NC List = 197, 242, 257, 288, 27, 31 | G16: 1. For each Denied PC claim, strip prefix from primary code and test against NC List. | H16: No Denied PC claim has an NC primary code. | I16: 5,245 Denied PC; 0 with NC primary code. | J16: Pass | K16: Pass
A17: TC-016 | B17: AR Queue Logic | C17: §3.1, §3.2, AT-3 | D17: High | E17: Denied – Non-Collectible: primary on NC List; visible only to Admin/Mgr/TL | F17: Primary 197 / 27 / 31 etc. | G17: 1. Verify placement via API. 2. Verify visibility as AR Agent / QA. | H17: Placed in Denied – Non-Collectible; hidden from Agent/QA. | I17: 249 Denied NC (all NC primary). Visibility: ARAgent1 0, QA1 0, TeamLead 248, Admin 249. | J17: Pass | K17: Partial | L17: DEF-16 fixed
A18: TC-017 | B18: AR Queue Logic | C18: §3.1 | D18: High | E18: Partially Paid – Possible Collectible / Non-Collectible split uses the same NC List | F18: All claims (API) | G18: 1. Check NC flag vs sub-queue. | H18: PC: primary not on NC List; NC: primary on NC List. | I18: 268 PP-PC / 2 PP-NC consistent with NC list. | J18: Pass | K18: Pass
A19: TC-018 | B19: AR Queue Logic | C19: §3.1 | D19: High | E19: Partially Adjusted: no denial, some CPTs adjusted, Ins Bal > 0 | F19: All claims (API) | G19: 1. Check denial code and balance on Partially Adjusted claims. | H19: No denial; Ins Bal > 0; auto-fed. | I19: 53 Partially Adjusted; 0 with denial. | J19: Pass | K19: Pass
A20: TC-019 | B20: AR Queue Logic | C20: §3.1, AT-6 | D20: High | E20: Patient AR: Pt Bal > 0 and Ins Bal = 0; denials ignored | F20: All claims (API) | G20: 1. Check all Patient AR claims. 2. Check no Pt-only-balance claim outside Patient AR. | H20: All Patient AR claims meet rule; none misplaced, even when a denial is present. | I20: 11,561 Patient AR all Pt Bal > 0 & Ins Bal = 0; 7 Pt-only claims held in Status Change Verification. | J20: Pass | K20: Pass | L20: OBS-20
A21: TC-020 | B21: AR Queue Logic | C21: §3.1, Features #7, #8 | D21: High | E21: Workflow queues exist: CIP Pending, CIP Response Received, Re-Follow-Up (Unresolved / New Denials), Submitted for QA, QA Rejected, Completed, Auto Adjustments | F21: Queue taxonomy (queues API) | G21: 1. Review queue list. | H21: All workflow queues and sub-queues defined. | I21: All workflow queues present incl. Re-Follow-Up (Unresolved / New Denials), Auto Adjustments (System / Approved Write-Offs), Status Change Verification; Unbilled (841) still extra. | J21: Pass | K21: Pass | L21: OBS-06
A22: TC-021 | B22: AR Queue Logic | C22: §3.2 | D22: High | E22: Only unresolved claims in the 4 Possible Collectible queues auto-flow into the Work Queue for assignment | F22: Nav badge 'Denial & AR Work Queue' = 9,054; Dashboard 'Claims Awaiting Assignment' = 83,986 | G22: 1. Reconcile unassigned counts by queue. 2. Compare with badge and dashboard KPI. | H22: Awaiting-assignment count = unassigned claims in Non-Responder, Denied PC, Partially Paid PC, Partially Adjusted only (7,193). | I22: Work Queue badge 7,218 = unassigned Denied PC 5,199 + PP PC 256 + Partially Adjusted 53 + Non-Responder 1,710. Dashboard 'Claims Awaiting Assignment' = 7,218. | J22: Pass | K22: Fail | L22: DEF-05, DEF-06 fixed
A23: TC-022 | B23: Configuration | C23: §3.2, Feature #2 | D23: High | E23: Non-Collectible list maintained in settings and drives the Denied & Partially Paid splits | F23: Master Values > Workbench Lists > Non-Collectible Denial Codes | G23: 1. Open list. 2. Compare with Denial Code Master 'Non-Collectible' flags. | H23: Single configurable NC list, stored without prefix, used by the queue engine. | I23: Workbench NC list (197, 242, 29, 119, 193, 204, 243, 279, 284) drives the queues correctly. Validated 20 Oct for code 284: all 24 claims with primary denial 284 are in Denied – Non-Collectible with isNonCollectible = true, e.g., 19460085 (CO284, $437.46) and 19385515 (CO284, $313.18). Denial Code Master flags the same NC set; 284 is not in the Denial Code Master at all (no row), so it has no master description / NC flag there. | J23: Pass | K23: Partial | L23: DEF-07 fixed; OBS-28
A24: TC-023 | B24: Roles & Access | C24: §10 (Maintain NC & Auto-Adjust lists) | D24: Medium | E24: AR/RCM Manager can maintain NC and Auto-Adjust lists | F24: App navigation role config | G24: 1. Inspect role access for Master Values. | H24: Sys Admin and AR/RCM Manager can maintain. | I24: RCMManager: Master Values › Workbench Lists (NC + Auto-Adjust only) with Add/Deactivate; masters API 200. | J24: Pass | K24: Fail | L24: DEF-08 fixed
A25: TC-024 | B25: Roles & Access | C25: §3.2, AT-3 | D25: High | E25: Restricted (overall AR) queues visible only to Admin / Mgr / TL; they can pull any claim for special projects | F25: Admin session | G25: 1. As Admin, view all queues and assign. 2. As Agent/QA, confirm restricted queues hidden. | H25: Admin/Mgr/TL see and assign from any queue; Agent/QA cannot see Closed / NC queues. | I25: Admin/Mgr/TL see all queues (TL: NC 248, Closed-Paid 43,003). Agent limited to own 23 claims. QA API limited to 7,416 open priority claims, NC = 0. | J25: Pass | K25: Partial | L25: DEF-16 fixed
A26: TC-025 | B26: AR Queue Logic | C26: §3.2 | D26: High | E26: QA Rejected claims auto-assigned to the agent who worked them | F26: Claim 19091270 | G26: 1. Open claim timeline and assignment fields. | H26: Rejected claim assigned back to the submitting agent. | I26: 19510576 rejected by QA1 → QA Rejected, assigned to ARAgent1. | J26: Pass | K26: Pass
A27: TC-026 | B27: AR Queue Logic | C27: §3.2 (To confirm) | D27: Low | E27: Evaluation precedence when a claim meets more than one rule | F27: All claims | G27: 1. Check for claims meeting multiple rules. | H27: Deterministic precedence (recommended Closed → Patient AR → Denied → Partially Paid → Partially Adjusted → Non-Responder). | I27: No claim in more than one queue; precedence consistent with §18.3. | J27: Pass | K27: Pass
A28: TC-027 | B28: Denial Logic | C28: §4.1 | D28: High | E28: Primary denial = curated 'Denial Code' column (interim) | F28: Settings API | G28: 1. Read settings PrimaryDenialSource / FallbackToLine. | H28: Curated column used; no line-level fallback. | I28: PrimaryDenialSource = CuratedColumn; FallbackToLine = 0. | J28: Pass | K28: Pass
A29: TC-028 | B29: Denial Logic | C29: §4.1, Feature #15 | D29: Low | E29: Denial-hierarchy ranking table to derive primary denial (terminal codes override) | F29: — | G29: — | H29: Configurable ranking table; e.g., 204/197 override other codes. | I29: Phase 2 – not tested. | J29: N/A (Phase 2) | K29: N/A (Phase 2)
A30: TC-029 | B30: Denial Logic | C30: §4.2, AT-4, Feature #5 | D30: High | E30: CARC group prefix (CO/PR/PI/OA) stripped for mapping | F30: PR204 (25 claims), CO204 (13 claims); PRA1, PIB11 | G30: 1. Compare category for prefixed variants of the same code. | H30: PR 204 and CO 204 both map to 204 and the same category. | I30: PR204 / CO204 → 204 → same category; CR96 now normalised and mapped. | J30: Pass | K30: Pass | L30: OBS-08 fixed
A31: TC-030 | B31: Denial Logic | C31: §4.2, AT-5 | D31: Medium | E31: RARC codes keep their letter (e.g., N57, M127, MA130) | F31: Claim data and Denial Code Master | G31: 1. Search for N57 / RARC codes. | H31: Stored and mapped as N57 (letter retained). | I31: No N57 / M127 / MA130 in claim data or Denial Code Master (116 codes); cannot exercise. | J31: Blocked | K31: Blocked | L31: Test data
A32: TC-031 | B32: Denial Logic | C32: §4.3 | D32: High | E32: Denial categorization for all denial codes loaded into the Denial-Action master | F32: Workbench Category Map / Unmapped Codes | G32: 1. Review category map coverage. 2. Review Unmapped Codes. | H32: Every primary denial code on synced claims has a category. | I32: Only 1 unmapped primary code (CO17, 2 claims); 110 of 5,839 denied claims (1.9%) categorised Other/blank. | J32: Pass | K32: Fail | L32: DEF-09 fixed
A33: TC-032 | B33: Denial Logic | C33: §4.2 | D33: Low | E33: Line-level display keeps original prefix but is not used for mapping | F33: Claim 19448764 | G33: 1. View line-level denials. | H33: Prefixed value shown; mapping uses stripped code. | I33: Line display keeps CO11 / CO252; mapping uses 11 / 252. | J33: Pass | K33: Pass
A34: TC-033 | B34: Weekly Re-Sync | C34: §5, AT-10 | D34: High | E34: Assigned, not-yet-worked claim whose denial changes: update silently; if new primary is NC, auto-process and remove from agent queue | F34: Requires a sync with changed denial data | G34: 1. Assign claim. 2. Load sync file with new (NC) denial. 3. Check agent queue. | H34: Denial updated without reassignment; NC claim auto-processed and removed. | I34: Sync 16–18 Oct: denial changes logged ('Denial Code Changed … on sync'); assigned claims whose claim status changed were held in Status Change Verification (14) with manager notifications. No assigned claim moved to an NC primary in this sync, so NC auto-process path not observed. | J34: Partial | K34: Not Executed | L34: OBS-20
A35: TC-034 | B35: Weekly Re-Sync | C35: §5, AT-9, Feature #7 | D35: High | E35: Worked claim (QA/Completed/QA Rejected) receives a new denial → after QA completes, moves to Re-Follow-Up – New Denials, unassigned, history intact | F35: Requires a sync with a new denial on a completed claim | G35: 1. Complete claim. 2. Re-sync with new denial. | H35: Claim in Re-Follow-Up – New Denials, unassigned, full history. | I35: No worked claim received a new denial in this sync (New Denials sub-queue 0; NewDenialSinceWork / PreviousPrimaryDenialCode fields exist). | J35: Not Executed | K35: Not Executed | L35: Next sync
A36: TC-035 | B36: Weekly Re-Sync | C36: §5, §3.1 | D36: High | E36: Followed-up claim with no reply/action for 45 days → Re-Follow-Up – Unresolved Claims | F36: RefollowupDays = 45 | G36: 1. Identify claims with last touch ≥ 45 days. | H36: Claims ≥ 45 days since last touch appear in Unresolved queue. | I36: RefollowupDays = 45; earliest worked follow-up 07 Oct → first eligible 21 Nov 2026. | J36: Blocked | K36: Blocked | L36: Time-based
A37: TC-036 | B37: Weekly Re-Sync | C37: §5, §6, AT-12, Feature #9 | D37: High | E37: Auto-adjusted / approved write-off claim still open on next sync → flagged, returned to Auto Adjustments, agent & manager notified | F37: Requires processed auto-adjustment + re-sync | G37: 1. Process auto adjustment. 2. Re-sync with claim still open. | H37: Flag + return + notification. | I37: 19510788 (never posted), 19122637 and 19521528 (marked posted, still open in master) flagged 'Adjustment Not Posted', returned to Auto Adjustments (System / Approved Write-Offs); ARAgent1 notified; RCMManager received 36 AdjustmentNotPosted notifications. | J37: Pass | K37: Not Executed
A38: TC-037 | B38: Weekly Re-Sync | C38: §5 | D38: Medium | E38: Claim that now meets closed criteria moves to the relevant Closed queue | F38: Claims 19448701, 19446019, 19445909, 19454954, 19449830, 19449723, 19449752 | G38: 1. Check workflow status of Closed claims. | H38: Claim in Closed queue; recovered amount recognised. | I38: 19538684 closed via sync (Ins Bal 124.28 → 0, audit 'Source Data Updated') → Closed – Fully Adjusted. Assigned claims that close are held in Status Change Verification for manager decision (19580937 'Complete' → Closed – Fully Adjusted). | J38: Pass | K38: Partial | L38: OBS-20
A39: TC-038 | B39: Auto Adjustments | C39: §6 | D39: High | E39: Auto-Adjust code list is configurable | F39: Workbench Lists > Auto-Adjust Denial Codes | G39: 1. Open list. | H39: List maintainable; seeded with 242, 197. | I39: Auto-Adjust list 8 codes (242, 197, 29, 119, 193, 204, 243, 279). | J39: Pass | K39: Pass
A40: TC-039 | B40: Auto Adjustments | C40: §6, Feature #8 | D40: High | E40: Process Auto Adjustment: adds system comment, nullifies balance, moves claims to Auto Adjustments queue | F40: Work Queue > Process Automatic Adjustments | G40: 1. Run preview / process on matching claims. | H40: Claims moved to Auto Adjustments (not Completed) with system comment and $0 balance. | I40: Processed by Admin (19497919), TeamLead (19492367) and RCMManager (19491057): system comment, Auto Adjustments › System Auto-Adjusted. Screens show the balance nullified — 19497919 Claim Detail: Insurance Balance $0.00, Adjustments $228.86, Outstanding $0.00; Work Queue Ins. Balance $0 (confirmed by RSKP screenshot). Note: the raw claims-API field InsuranceBalance still carries the source value 228.86 with isBalanceNullified = true; RemainingAR = 0. | J40: Pass | K40: Pass | L40: DEF-20 fixed (UI); OBS-26
A41: TC-040 | B41: Auto Adjustments | C41: §6, §10 | D41: High | E41: Admin / Mgr / TL can export the Auto Adjustments queue as a report for bulk PMS posting | F41: Work Queue export | G41: 1. Filter AR Queue = Auto Adjustments. 2. Export. | H41: Dedicated export of Auto Adjustments queue. | I41: Auto Adjustments queue filterable; exports run as background jobs in My Downloads (.xlsx). | J41: Pass | K41: Pass
A42: TC-041 | B42: Financial Fields | C42: §7, Feature #6 | D42: Medium | E42: 'Expected Payment' renamed to 'Revenue Expectation' everywhere | F42: Claim detail; Work Queue grid | G42: 1. Open claim detail. 2. Open Work Queue columns. | H42: Label reads 'Revenue Expectation' in all views. | I42: 'Revenue Expectation' in Work Queue grid, column picker and Claim Detail; 'Expected Payment' no longer in the app. | J42: Pass | K42: Fail | L42: DEF-10 fixed
A43: TC-042 | B43: Financial Fields | C43: §7 | D43: High | E43: Revenue Expectation = Medicare-rate allowable across billed CPTs (0 if no rate) | F43: All claims | G43: 1. Check RevenueExpectation values. 2. Compare with dashboard 'revenue expectation by AR queue'. | H43: Calculated from fee schedule for each claim. | I43: Revenue Expectation populated for 84,481 / 84,494 claims (Medicare fee rate × units per CPT). Per RSKP clarification (19 Oct), RE is calculated only for collectible Denied / No Response CPT lines — paid (and partially adjusted) lines are excluded. Observed behaviour matches: 19448764 counts only denied lines 87481 ($175.45) + 87640 ($35.09) = $210.54; 19543579 counts only 80307 ($62.14). | J43: Pass | K43: Fail | L43: DEF-21 withdrawn; OBS-27
A44: TC-043 | B44: Financial Fields | C44: §7, AT-8 | D44: High | E44: Potential Recovery = Revenue Expectation − (Ins Paid + Pt Paid + Pt Bal), floor 0 | F44: AT-8 case: RevExp $353, Ins paid $120, Pt bal $30 | G44: 1. Locate claim matching case. 2. Check Potential Recovery. | H44: Potential Recovery $203. | I44: Potential Recovery = max(0, RevExp − (Ins Pmt + Pt Pmt + Pt Bal)) verified on 141/141 sampled claims; dashboard total $2,044,885.55. | J44: Pass | K44: Blocked | L44: DEF-11 fixed
A45: TC-044 | B45: Financial Fields | C45: §7, AT-8 | D45: Medium | E45: Recovery Status: In Progress / Partially Recovered / Fully Recovered / No Recovery | F45: Claim 19448764 (all payments 0) | G45: 1. Open claim Overview. | H45: In Progress when Ins paid, Pt paid and Pt bal are all 0. | I45: 22 of 141 sampled claims have the wrong Recovery Status: Patient AR claims with Pt Bal > 0 show 'In Progress' (8,347 Patient AR claims overall). | J45: Fail | K45: Partial | L45: DEF-22
A46: TC-045 | B46: Financial Fields | C46: §7 | D46: High | E46: Recovered Amount = insurance payments dated after denial date; adjustments excluded | F46: Recovery & Financial Analytics | G46: 1. Read metric definition and totals. | H46: Payments only, after denial date. | I46: Analytics definition: 'insurance payments dated after the claim's denial date … payments only; adjustments and write-offs are not recovery'. Total Recovered $29,314.64. | J46: Pass | K46: Fail | L46: DEF-12 fixed
A47: TC-046 | B47: Follow-Up | C47: §8.1 | D47: Medium | E47: Follow-up notes captured at claim level only (no CPT-level notes) | F47: Claim 19448764 > Log Follow-Up Note | G47: 1. Open note form. | H47: Claim-level note only. | I47: Follow-up form is claim-level only. | J47: Pass | K47: Pass
A48: TC-047 | B48: Follow-Up | C48: §8.1, AT-15 | D48: High | E48: Next Follow-Up Date defaults to today + 45 calendar days | F48: Test date Oct 15, 2026 | G48: 1. Open Log Follow-Up Note. 2. Read default date. | H48: Default = Nov 29, 2026. | I48: Default next follow-up 03 Dec 2026 on 19 Oct (= +45); min = today, no max. | J48: Pass | K48: Pass | L48: OBS-12
A49: TC-048 | B49: Attachments | C49: §8.2, Feature #11 | D49: High | E49: Attachments available on follow-up notes for ALL actions | F49: Log Follow-Up Note form | G49: 1. Open form for each Claim Status / Fix-Resolution. 2. Look for file upload. | H49: Upload control on every follow-up note. | I49: Log Follow-Up Note has 'Documents' section (up to 5 files, 15 MB each); 19514348 saved with 1 document. | J49: Pass | K49: Fail | L49: DEF-13 fixed
A50: TC-049 | B50: Attachments | C50: §8.2 | D50: High | E50: Each upload requires a document category | F50: Document Categories list (6) | G50: 1. Attempt upload. | H50: Category mandatory (Appeal, EOB, Medical Record, Payer Correspondence, CIP Response, Other). | I50: Save blocked: 'UAT_big_16MB.pdf: choose a document category.'; categories Appeal/EOB/Medical Record/Payer Correspondence/CIP Response/Other. | J50: Pass | K50: Fail | L50: DEF-13 fixed
A51: TC-050 | B51: Attachments | C51: §8.2 | D51: High | E51: Document Vault: search documents by claim/visit, patient and category | F51: Navigation | G51: 1. Look for Document Vault. | H51: Document Vault screen available. | I51: Document Vault: search by claim/visit/patient, category, source (follow-up / CIP), date range; follow-up attachment listed with category Appeal. | J51: Pass | K51: Fail | L51: DEF-14 fixed
A52: TC-051 | B52: Attachments | C52: §8.2 | D52: High | E52: Files stored in Azure Blob with HIPAA controls (encryption at rest, private access, RBAC, audit logging) | F52: Setting DocumentBlobContainer = arwb-documents | G52: 1. Infrastructure review. | H52: Blob storage with HIPAA controls. | I52: Container setting present; Azure Blob encryption/private access/audit needs infra review. | J52: Not Executed | K52: Not Executed | L52: Infra review
A53: TC-052 | B53: Attachments | C53: §8.2, AT-16 | D53: Medium | E53: Uploading a 20 MB file is rejected with a size-limit message | F53: AttachmentMaxBytes = 15,728,640 (15 MB) | G53: 1. Upload 20 MB file. | H53: Rejected with size-limit message. | I53: 16 MB file rejected on follow-up save ('larger than 15 MB') and on client CIP response. | J53: Pass | K53: Partial
A54: TC-053 | B54: Write-Off Approval | C54: §8.3, Feature #10 | D54: High | E54: Agent selects Write-Off → claim goes to Submitted for QA | F54: Log Follow-Up Note: Claim Status = Denied | G54: 1. Select Write Off. 2. Save. | H54: Claim routed to QA as a write-off. | I54: 19518771 Write Off → Submitted for QA. | J54: Pass | K54: Pass
A55: TC-054 | B55: Write-Off Approval | C55: §8.3, AT-11 | D55: High | E55: QA approves write-off → claim in 'Approved Write-Offs – Pending Posting' in agent's queue with notification; agent marks posted | F55: Requires write-off submission | G55: 1. QA approve. 2. Check agent queue + notification. 3. Mark as Posted. | H55: Pending-posting list + notification 'Write-off approved — perform the write-off in the PMS.' | I55: QA bulk approval → Approved Write-Offs – Pending Posting; ARAgent1 notified; ARAgent1 marked 19521528 as posted (API 200). | J55: Pass | K55: Partial | L55: DEF-17 fixed
A56: TC-055 | B56: Escalation / Reassignment | C56: §8.4, Feature #12 | D56: Medium | E56: Escalate to Supervisor with mandatory reason category; routed to TL and AR Manager | F56: Escalation Reasons (6) | G56: 1. As agent, escalate. 2. Check Escalation & Reassignment Requests. | H56: Mandatory reason dropdown + free text; visible to TL and Mgr. | I56: 19085340 escalated: reason mandatory; claim stays Assigned to agent; TeamLead bulk-resolved with mandatory note. | J56: Pass | K56: Pass
A57: TC-056 | B57: Escalation / Reassignment | C57: §8.4, Feature #12 | D57: Medium | E57: Request Reassignment with mandatory reason category | F57: Reassignment Reasons (5) | G57: 1. As agent, request reassignment. | H57: Mandatory reason dropdown + free text. | I57: 19052061 reassignment request (reason 'Workload / capacity') → TeamLead Reassign & Resolve → ARAgent3; request auto-resolved. | J57: Pass | K57: Pass
A58: TC-057 | B58: Assignment | C58: §8.5, Feature #13 | D58: Medium | E58: Due Date on batch assignment is optional | F58: Assignment Management > Create Assignment Batch | G58: 1. Review batch form. 2. Review existing batch. | H58: Due Date optional; applies to every claim in batch. | I58: Batch Due Date optional; BATCH-0001 due 23 Oct; direct assign with due date 23 Oct. | J58: Pass | K58: Pass
A59: TC-058 | B59: CIP Workflow | C59: §9.1 | D59: High | E59: Selecting CIP requires internal Follow-Up Comment + client-facing CIP Comment; CIP box only when CIP selected | F59: Log Follow-Up Note; Fix/Resolution = CIP - Client Escalations | G59: 1. Toggle resolution between CIP / non-CIP. | H59: CIP Comment appears only for CIP and is mandatory. | I59: CIP Category / Required Information / CIP Comment shown only for CIP; saved on 19521746 and 19375256. | J59: Pass | K59: Pass
A60: TC-059 | B60: CIP Workflow | C60: §9.1 | D60: High | E60: CIP note goes to Submitted for QA; QA by QA Reviewer / TL / RCM Mgr | F60: Claim 18955927 | G60: 1. Review activity timeline. | H60: Routed to QA; after QA approval enters CIP Pending Approval. | I60: QA bulk approval: '2 CIP escalation(s) now Pending Approval'. | J60: Pass | K60: Pass
A61: TC-060 | B61: CIP Workflow | C61: §9.1 | D61: High | E61: CIP Escalations – Pending Approval accessible only to TL, RCM Mgr, Admin; individual or bulk approval | F61: CIP Escalations screen | G61: 1. Open screen. 2. Check roles and bulk actions. | H61: Second approval layer with bulk approve. | I61: TeamLead: 'Approve & Send to Client' (CIP-000004) and Bulk Approve (CIP-000005). | J61: Pass | K61: Pass
A62: TC-061 | B62: CIP Workflow | C62: §9.1 | D62: High | E62: Approved CIPs appear in client's Escalation Requests tab | F62: Requires approval + client login | G62: 1. Approve CIP. 2. Log in as client. | H62: CIP visible to scoped client user. | I62: ClinicViewer sees CIP-000004; AccountManager sees CIP-000003/4/5; CIP-000001 (Pending Approval) hidden. | J62: Pass | K62: Pass
A63: TC-062 | B63: CIP Workflow | C63: §9.1, AT-13 | D63: High | E63: Client responds (with attachments) → Client Responded; manager re-escalates or approves → claim returns to original agent | F63: Requires client response | G63: 1. Client responds. 2. Manager approves. | H63: Claim auto-returns to original agent. | I63: ClinicViewer responded (PDF) → CIP Response Received → RCMManager Insufficient (note) → Round 2 → AccountManager responded → RCMManager Approve & Return → 19521746 and 19375256 Assigned to ARAgent1. | J63: Pass | K63: Pass | L63: DEF-19 fixed
A64: TC-063 | B64: CIP Workflow | C64: §9.2 | D64: High | E64: Internal follow-up comments and client-facing CIP comments stored and displayed separately; client never sees internal notes | F64: Claim 18955927 | G64: 1. Review stored fields. 2. View as client. | H64: Separate storage; client sees only CIP comment + response. | I64: Client claim page shows only Overview / CPT / Denial Info / Documents; claim API returns no internal notes (ClinicViewer and AccountManager; old claim 19524452 too). | J64: Pass | K64: Fail | L64: DEF-15 fixed
A65: TC-064 | B65: Roles & Access | C65: §10 | D65: Medium | E65: Navigation/permissions match the role matrix | F65: App role configuration | G65: 1. Compare each screen's roles with §10 matrix. | H65: Matches matrix. | I65: Server-enforced matrix aligned for all 7 roles. Deviations: Analytics / Reports / Document Vault open to Agent & QA; QA grid shows a checkbox on ineligible (own-work) rows. | J65: Partial | K65: Partial | L65: OBS-13, DEF-30
A66: TC-065 | B66: User Management | C66: §10.1, Feature #14 | D66: High | E66: Admin creates client users scoped Lab → Clinic with cascading selection | F66: User Management > Add User | G66: 1. Choose role Clinic Viewer. 2. Select lab. | H66: Selecting a lab loads only that lab's clinics. | I66: Add User: Client / Clinic / Provider Viewer; cascading clinic picker; Azure AD users tab present. | J66: Pass | K66: Pass
A67: TC-066 | B67: User Management | C67: §10.1, AT-14 | D67: High | E67: Clinic-scoped user sees only that clinic's data and CIPs; never internal notes | F67: Requires Clinic Viewer login | G67: 1. Log in as clinic user. | H67: Only Clinic A data / CIPs. | I67: ClinicViewer: 7,300 claims all Insight Family Practice; Spark to Recovery claim 404; no internal notes. | J67: Pass | K67: Fail | L67: DEF-15 fixed
A68: TC-067 | B68: User Management | C68: §10.1 | D68: Medium | E68: CIP escalations for a clinic routed to that clinic's scoped user(s) | F68: Requires Clinic Viewer login | G68: 1. Approve CIP for a clinic. 2. Check scoped user. | H68: Routed to scoped user. | I68: ClinicViewer has Respond and answered CIP-000004 with attachment. | J68: Pass | K68: Partial | L68: DEF-18 fixed
A69: TC-068 | B69: Export / Import | C69: Project instructions | D69: Medium | E69: AR users can export claims to Excel and update status via Excel upload | F69: Work Queue toolbar | G69: 1. Review export / bulk update options. | H69: Export and bulk update available. | I69: Export Filtered / All / Excel → background jobs in My Downloads; Bulk Update (Excel) present (upload not executed). Client users have Reports export only — no claim/line-item export. | J69: Partial | K69: Partial | L69: DEF-29

Sheet Part B FR Traceability
A1: Req ID | B1: Module | C1: Requirement (summary) | D1: Status (19 Oct) | E1: Evidence / Actual Result | F1: Defect / Obs Ref
A2: FR-ACC-01 | B2: Roles & Scoping | C2: One role + one access grant (All / Client / Clinic / Provider) | D2: Pass | E2: Add User offers Client, Clinic, Provider Viewer with per-lab clinic picker.
A3: FR-ACC-02 | B3: Roles & Scoping | C3: Central scoping on every screen, count, export, API | D3: Pass | E3: Agent 23 claims everywhere; QA 7,416; ClinicViewer 7,300 (claims, queues, dashboard, vault). | F3: DEF-16 fixed
A4: FR-ACC-03 | B4: Roles & Scoping | C4: Fixed scope badge for scoped users | D4: Pass | E4: Header 'Clinic: Insight Family Practice' / 'Client: Inhealth_DTR'.
A5: FR-ACC-04 | B5: Roles & Scoping | C5: Single route/role declaration for nav, routing and API | D5: Pass | E5: UI 'Your role … cannot open …' plus API 403 for the same screens.
A6: FR-ACC-05 | B6: Roles & Scoping | C6: Agent sees only own claims in every view | D6: Pass | E6: Work Queue, My Work, queues API = 23; other claim 404.
A7: FR-ACC-06 | B7: Roles & Scoping | C7: Client users never see internal notes on escalated claims | D7: Pass | E7: No Follow-Ups / Activity / QA tabs; API clean. | F7: DEF-15 fixed
A8: FR-NAV-01 | B8: Navigation | C8: Land on first permitted screen | D8: Pass | E8: Agent → My Work; Clinic Viewer → Escalation Requests; Admin → Dashboard.
A9: FR-NAV-02 | B9: Navigation | C9: Badge = destination list predicate | D9: Pass | E9: Work Queue badge 7,218 = unassigned PC claims; QA badge = awaiting QA rows.
A10: FR-NAV-03 | B10: Navigation | C10: Header shows refresh date and source period | D10: Pass | E10: 'master file loaded Oct 18 · synced Oct 18'; source period on Data Processing.
A11: FR-NAV-04 | B11: Navigation | C11: Claim Detail Back returns to originating screen | D11: Partial | E11: Back link always reads '← Back to Work Queue' (also from CIP / client screens). | F11: OBS-21
A12: FR-DP-01 | B12: Data Processing | C12: Refresh date, source period, counts, Run action | D12: Pass | E12: Run Master File Load / Run Data Processing (admin, manager).
A13: FR-DP-02 | B13: Data Processing | C13: Run executes sync → normalise → classify → insights with logged progress | D13: Not Executed | E13: Run log present (Master File Loads, Run history); a run was not triggered by the tester.
A14: FR-DP-03 | B14: Data Processing | C14: Insights table columns | D14: Pass | E14: All listed columns present incl. Still Open.
A15: FR-DP-04 | B15: Data Processing | C15: Insights by primary code; open, unassigned only | D15: Pass | E15: 216: 2,219 / $773,349.77 matches recompute.
A16: FR-DP-05 | B16: Data Processing | C16: Highest $ impact payer & % | D16: Pass | E16: BCBS-MT, 100%.
A17: FR-DP-06 | B17: Data Processing | C17: Observation & recommended action text | D17: Pass | E17: Observation and action from Key Observations.
A18: FR-DP-07 | B18: Data Processing | C18: Route to Work Queue with removable insight chip | D18: Not Retested | E18: 15 Oct: chip 'Denial Code: CO-216'; 1,700 vs 1,699 rows. | F18: OBS-02
A19: FR-DP-08 | B19: Data Processing | C19: Dashboard top-5 current week; DP full list | D19: Pass | E19: Dashboard shows current-week uploaded insight.
A20: FR-ARQ-01 | B20: AR Queue Engine | C20: Queue taxonomy as master data | D20: Pass | E20: queues API returns taxonomy with labels, priority flags.
A21: FR-ARQ-02 | B21: AR Queue Engine | C21: Queue badge 'Top · Sub' on lists & detail | D21: Pass | E21: e.g. 'Denied · Possible Collectible'.
A22: FR-ARQ-03 | B22: AR Queue Engine | C22: Recompute after sync/action; nightly snapshot | D22: Pass | E22: Snapshots daily to 19 Oct; queues update immediately after actions.
A23: FR-ARQ-04 | B23: AR Queue Engine | C23: Non-priority leaves admin/mgr/lead only; ad-hoc assignment flagged | D23: Pass | E23: 18954330 (Closed) assigned → AdHocFollowUpAssigned = true, audit 'Ad-Hoc Assignment'.
A24: §18.3 | B24: AR Queue Engine | C24: Precedence table (first match wins) | D24: Pass | E24: Full reconciliation of 84,494 claims; 0 rule exceptions.
A25: FR-DASH-KPI | B25: Dashboard | C25: 10 KPI tiles per definitions | D25: Pass | E25: All tiles present; Potential Recovery $2.04M; Recovered $29,314.64; Awaiting Assignment 7,218.
A26: FR-DASH-01 | B26: Dashboard | C26: Standard widgets | D26: Pass | E26: Insights, AR Collections Progress, Queue Volumes, Category, Aging, Workflow, Recovery donut, Agent Productivity.
A27: FR-DASH-02 | B27: Dashboard | C27: Control Plan widget (Open / In Progress / Closed by classification & action) | D27: Fail | E27: Not present. | F27: DEF-23
A28: FR-DASH-03 | B28: Dashboard | C28: SLA attainment, Appeal Success Rate tiles | D28: Fail | E28: Not present (Operational SLA exists only as a report). | F28: DEF-23
A29: FR-DASH-04 | B29: Dashboard | C29: Scoped widgets; bar click opens Work Queue | D29: Not Retested
A30: FR-WQ-01 | B30: Work Queue | C30: Agent base population vs full register | D30: Pass | E30: Agent 23 own; admin 84,494.
A31: FR-WQ-02 | B31: Work Queue | C31: Primary filters | D31: Pass | E31: Search, Clinic, Payer, Panel, Category, Status, Agent, Priority, Aging, AR Queue, TFL.
A32: FR-WQ-03 | B32: Work Queue | C32: More filters (Claim Status, Rendering Provider, Fix, CPT, balance, next FU range) | D32: Fail | E32: No 'More filters' on Work Queue (My Work has one). | F32: DEF-24
A33: FR-WQ-04 | B33: Work Queue | C33: Saved views (server) | D33: Pass | E33: Save View / Saved View selector; saved-views API.
A34: FR-WQ-05 | B34: Work Queue | C34: Columns incl. hidden-by-default set | D34: Pass | E34: Column picker incl. Denial Reason, Claim Status, Fix, Revenue Expectation, Recovered, Recovery Status, Remaining AR.
A35: FR-WQ-06 | B35: Work Queue | C35: Bulk assign; previous agent audited | D35: Pass | E35: 7 claims assigned; reassign audited.
A36: FR-WQ-07 | B36: Work Queue | C36: Process Automatic Adjustments (admin/mgr/lead) | D36: Pass | E36: Processed by all three roles.
A37: FR-WQ-08 | B37: Work Queue | C37: Claim-level rows | D37: Pass | E37: Row count = claims.
A38: FR-CD-01 | B38: Claim Detail | C38: Header badges & identifiers | D38: Pass | E38: Status, queue, priority, TFL badges; payer, panel, DOS, patient, provider, clinic.
A39: FR-CD-02 | B39: Claim Detail | C39: Stepper + category workflow path | D39: Pass | E39: Identified → Assigned → QA Verification → Completed + template path.
A40: FR-CD-03 | B40: Claim Detail | C40: Tabs incl. Documents | D40: Pass | E40: Overview, CPT, Denial Info, Follow-Ups, Activity, QA Review, Documents.
A41: FR-CD-04 | B41: Claim Detail | C41: Overview stat strip with S formulas | D41: Pass | E41: Revenue Expectation, Potential Recovery, Recovery Status shown.
A42: FR-CD-05 | B42: Claim Detail | C42: CPT columns + per-line denial expand | D42: Pass | E42: Expand per CPT with code, description, category; adds Fee Rate & Rev. Expectation columns.
A43: FR-CD-06 | B43: Claim Detail | C43: Denial Info fields | D43: Pass | E43: All fields incl. corrective action, TFL, supporting docs.
A44: FR-CD-07 | B44: Claim Detail | C44: Follow-Ups tab | D44: Pass | E44: Note cards with CIP block.
... A54: FR-ASG-01 | B54: Assignment | C54: Unassigned 45+ days list | D54: Pass | E54: 4,955 PC / Re-Follow-Up claims untouched 45+ days.
A55: FR-ASG-02 | B55: Assignment | C55: Batch criteria incl. Action filter; optional due date | D55: Partial | E55: Category, Payer, Panel, Priority, due date OK; no Action/Task filter (no Client filter – single lab). | F55: DEF-25
A56: FR-ASG-03 | B56: Assignment | C56: Batches log, server-persisted | D56: Pass | E56: BATCH-0001 persisted with completion %.
A57: FR-ASG-04 | B57: Assignment | C57: Agent workload chart | D57: Pass | E57: Open claims per agent.
A58: FR-ASG-05 | B58: Assignment | C58: Assigned Claims – Bulk Reassign | D58: Pass | E58: Section present (77 claims, incl. completed-but-unpaid).
A59: FR-ASG-06 | B59: Assignment | C59: Reassign resolves pending request | D59: Pass | E59: 19052061 'Resolved by reassigning to ARAgent3'.
A60: FR-ASG-07 | B60: Assignment | C60: Assigned claims leave insight counts | D60: Pass | E60: 216 still-open excludes assigned claims.
A61: FR-MW-01 | B61: My Work | C61: Agent own / lead team scope | D61: Pass | E61: Agent 23 claims.
A62: FR-MW-02 | B62: My Work | C62: KPI tiles incl. (N) Approved Write-Offs & New Denials | D62: Partial | E62: 9 standard tiles present; the two new tiles missing. | F62: DEF-26
A63: FR-MW-03 | B63: My Work | C63: Filters incl. More filters, saved views | D63: Pass | E63: Present.
A64: FR-MW-04 | B64: My Work | C64: Columns + Log Follow-Up action | D64: Pass | E64: Present.
A65: FR-FUM-01 | B65: Follow-Up Mgmt | C65: Actionable to-do queue | D65: Pass | E65: Claims drop off when logged.
A66: FR-FUM-02 | B66: Follow-Up Mgmt | C66: Window tiles | D66: Pass | E66: All Active / Overdue / Due Today / Upcoming / No Follow-Up.
A67: FR-FUM-03 | B67: Follow-Up Mgmt | C67: Filters | D67: Not Retested
A68: FR-FUM-04 | B68: Follow-Up Mgmt | C68: Overdue/today colouring | D68: Not Retested
A69: FR-FUM-05 | B69: Follow-Up Mgmt | C69: Re-follow-up 45-day logic | D69: Blocked | E69: Time-based (first eligible 21 Nov).
A70: FR-QA-01 | B70: QA | C70: Population & filters | D70: Pass | E70: Filters incl. Escalation, QA Reviewer.
A71: FR-QA-02 | B71: QA | C71: Columns & actions | D71: Pass | E71: Approve / Reject or Review.
A72: FR-QA-03 | B72: QA | C72: Self-approval blocked for every role | D72: Pass | E72: TeamLead own claim: Review only; API 409 'you cannot QA your own work'.
A73: FR-QA-04 | B73: QA | C73: Reject requires error type + note; returns to same agent | D73: Pass | E73: 'Add a note explaining what needs correcting.'
A74: FR-QA-05 | B74: QA | C74: Six scoring criteria | D74: Pass | E74: Shown in approve/reject dialogs.
A75: FR-QA-06 | B75: QA | C75: Bulk approve eligibility + summary | D75: Partial | E75: Summary shows count, $, CIP and write-off counts; but ineligible own-work row still has a checkbox. | F75: DEF-30
A76: FR-QA-07 | B76: QA | C76: CIP → Pending Approval; Write-Off → Pending Posting | D76: Pass | E76: Toast '2 CIP … 1 write-off(s) approved'.
A77: FR-REQ-01 | B77: Requests | C77: Escalate / Reassign with reason category | D77: Pass | E77: 'Choose a reason.' when missing.
A78: FR-REQ-02 | B78: Requests | C78: Request record fields | D78: Pass | E78: Type, reason, note, status, resolution.
A79: FR-REQ-03 | B79: Requests | C79: Queue filters & columns | D79: Pass | E79: Incl. Reason / Note column.
A80: FR-REQ-04 | B80: Requests | C80: Respond: Mark Resolved / Open Claim / Reassign & Resolve | D80: Pass | E80: Used on 19052061.
A81: FR-REQ-05 | B81: Requests | C81: Bulk resolve with shared note | D81: Pass | E81: 'Add a response note…' then '1 request resolved.'
A82: FR-REQ-06 | B82: Requests | C82: Escalation routing (stay with agent) | D82: Pass | E82: 19085340 stayed Assigned to ARAgent1 (recommended option).
A83: FR-CIP-01 | B83: CIP Internal | C83: Case record with rounds & history | D83: Pass | E83: Round 2, review notes, attachments per round.
A84: FR-CIP-02 | B84: CIP Internal | C84: Stage counts & columns incl. attachments | D84: Pass | E84: Attachment download links per row.
A85: FR-CIP-03 | B85: CIP Internal | C85: Review & Approve / Reject; Review Response | D85: Pass | E85: Approve & Send, Reject — Return to Agent, Insufficient, Approve & Return.
A86: FR-CIP-04 | B86: CIP Internal | C86: Bulk approve / send back | D86: Pass | E86: Bulk approve used on CIP-000005.
A87: FR-CIP-05 | B87: CIP Internal | C87: Default sort by stage | D87: Pass | E87: Client Responded first, then Pending, Sent, Returned.
A88: FR-CIP-06 | B88: CIP Internal | C88: Claim CIP tab read-only with queue link | D88: Not Retested
A89: FR-CIP-07 | B89: CIP Internal | C89: CIP queue exportable | D89: Pass | E89: Export present.
A90: FR-CLI-01 | B90: Client Portal | C90: Viewer scope; never Pending Approval | D90: Pass | E90: CIP-000001 hidden.
A91: FR-CLI-02 | B91: Client Portal | C91: Tiles | D91: Pass | E91: Awaiting / Submitted / Resolved.
A92: FR-CLI-03 | B92: Client Portal | C92: Columns incl. Reviewer Feedback | D92: Pass | E92: 'Needs more info' + reason on Round 2.
A93: FR-CLI-04 | B93: Client Portal | C93: Respond: text required + attachments ≤15 MB | D93: Pass | E93: 16 MB rejected; 1 PDF accepted.
A94: FR-CLI-05 | B94: Client Portal | C94: Bulk CSV template download / upload | D94: Partial | E94: Download / Upload Template present; upload not executed.
A95: FR-CLI-06 | B95: Client Portal | C95: Dashboard, Analytics, Reports scoped | D95: Pass | E95: Clinic Viewer data = 7,300 claims.
A96: FR-ADJ-01 | B96: Adjustments | C96: Eligibility by Auto-Adjust list | D96: Pass | E96: Preview only for listed codes with open balance.
A97: FR-ADJ-02 | B97: Adjustments | C97: Trigger by admin / manager / lead with confirmation | D97: Pass | E97: All three roles processed one claim each.
A98: FR-ADJ-03 | B98: Adjustments | C98: Remaining AR 0, system comment, Auto Adjustments queue | D98: Pass | E98: Balance shown as $0.00 on Claim Detail and Work Queue; system comment; Auto Adjustments queue. | F98: DEF-20 fixed; OBS-26
A99: FR-ADJ-04 | B99: Adjustments | C99: Export + Mark as Posted | D99: Pass | E99: Export via My Downloads; Mark as Posted (TL, agent).
A100: FR-ADJ-05 | B100: Adjustments | C100: Write-off loop; agent posts | D100: Pass | E100: Agent marked 19521528 posted. | F100: DEF-17 fixed
A101: FR-ADJ-06 | B101: Adjustments | C101: Re-appearance flag + notify agent & manager | D101: Pass | E101: 3 claims flagged; agent and manager notifications.
A102: FR-AN-01 | B102: Analytics | C102: KPI tiles | D102: Pass
A103: FR-AN-02 | B103: Analytics | C103: Recovered vs Outstanding by dimension | D103: Pass | E103: Client, Payer, Panel, Category, Agent, AR Queue.
A104: FR-AN-03 | B104: Analytics | C104: Follow-Up Comments Breakdown | D104: Pass | E104: 3 tabs, exportable.
A105: FR-AN-04 | B105: Analytics | C105: (N) Breakdown by escalation / reassignment reason | D105: Fail | E105: Not present. | F105: DEF-27
A106: FR-AN-05 | B106: Analytics | C106: Scoped analytics | D106: Pass | E106: Client viewers scoped.
A107: FR-RPT-01 | B107: Reports | C107: Summary reports exportable | D107: Pass | E107: 5 summaries + export.
A108: FR-RPT-02 | B108: Reports | C108: AR Collections Progress with confidence tiers | D108: Pass | E108: 100/50/30% columns, Yet to Collect, Payments Posted.
A109: FR-RPT-03 | B109: Reports | C109: Complex client report (open item) | D109: N/A (Open item) | E109: Awaiting walkthrough.
...

Sheet Part C Mockup Rules
A1: # | B1: Topic | C1: Build this (decision) | D1: Status | E1: Evidence
A2: 1 | B2: Data synced | C2: Full master synced; all claims classified | D2: Pass | E2: 84,494 claims classified.
A3: 2 | B3: Non-Responded rule | C3: Whole balance in insurance; no payment/denial/adjustment | D3: Pass | E3: 0 exceptions.
A4: 3 | B4: Non-collectible test | C4: Primary code only | D4: Pass | E4: NC split matches first code.
A5: 4 | B5: Code format | C5: Strip CO/PR/PI/OA; keep RARC letters | D5: Pass | E5: RARC not testable (no data).
A6: 5 | B6: Insight grouping | C6: Primary code; unassigned open only | D6: Pass | E6: 216 recompute matches.
A7: 6 | B7: Next follow-up default | C7: +45 days | D7: Pass | E7: 03 Dec on 19 Oct.
A8: 7 | B8: Re-Follow-Up queue | C8: Two sub-queues | D8: Pass | E8: Unresolved / New Denials exist.
A9: 8 | B9: Auto adjustment result | C9: Auto Adjustments queue + export + posted confirmation | D9: Pass | E9: Mark as Posted; re-appearance flag.
A10: 9 | B10: Write-off | C10: QA → Pending Posting → agent posts | D10: Pass | E10: Agent posted 19521528.
A11: 10 | B11: CIP case creation | C11: Visible only after QA approval | D11: Pass | E11: Pending Approval after QA.
A12: 11 | B12: Revenue Expectation | C12: Medicare-rate allowable; 0 if unavailable | D12: Pass | E12: Rate applied to collectible Denied / No Response lines only (rule clarified by RSKP; see OBS-27).
A13: 12 | B13: Potential Recovery | C13: RevExp − (Ins + Pt Pmt + Pt Bal) | D13: Pass | E13: 141/141.
... A23: 22 | B23: Line-level denials | C23: Expandable per-CPT detail | D23: Pass | E23: Expand per CPT.

Sheet Part E NFR
A1: ID | B1: Requirement | C1: Status | D1: Evidence
A2: NFR-01 | B2: Security: role & scope enforced server-side | C2: Pass | D2: Agent / QA / Client probes return 403/404 or scoped data; DEF-15 & DEF-16 fixed.
A3: NFR-02 | B3: HIPAA: encryption, signed URLs, download audit, timeout | C3: Not Executed | D3: Infra review required.
A4: NFR-03 | B4: Audit append-only | C4: Not Executed | D4: No edit/delete function exposed in UI; DB-level not verified.
A5: NFR-04 | B5: Multi-tenancy by lab | C5: Not Executed | D5: Single test lab available.
A6: NFR-05 | B6: Performance: server-side paging/filters | C6: Pass | D6: All grids page server-side; 1,000-row pages return < 1 s.
A7: NFR-06 | B7: Idempotent, recoverable sync | C7: Not Executed | D7: Sync not triggered by tester.
A8: NFR-07 | B8: One shared predicate implementation | C8: Pass | D8: Badges = lists = dashboard (7,218).
A9: NFR-08 | B9: Export formula-injection protection | C9: Not Executed
A10: NFR-09 | B10: Automated tests per module | C10: N/A | D10: Process requirement.

Sheet Role Workflow Retest
A1: Step ID | B1: Role | C1: Login | D1: Scenario / Requirement | E1: Claim(s) | F1: Action Performed | G1: Expected Result | H1: Actual Result | I1: Status | J1: Defect Ref
A2: RW2-01 | B2: System Administrator | C2: ARWBInhealthSA | D2: Assign 7 claims with due date (§8.5) | E2: 19514348, 19510576, 19518771, 19521746, 19085340, 19052061, 19375256 | F2: Assign → ARAgent1, due 23 Oct | G2: Assigned | H2: '7 assigned — ARAgent1.' | I2: Pass
A3: RW2-02 | B3: System Administrator | C3: ARWBInhealthSA | D3: Ad-hoc assignment of Closed claim (FR-ARQ-04) | E3: 18954330 | F3: Assign → ARAgent3 | G3: Flag adHoc + audit | H3: AdHocFollowUpAssigned = true; audit 'Ad-Hoc Assignment' | I3: Pass
A4: RW2-03 | B4: System Administrator | C4: ARWBInhealthSA | D4: Auto adjustment (§6) | E4: 19497919 | F4: Preview → Process | G4: Auto Adjustments; balance nullified | H4: Queue + system comment; Claim Detail & Work Queue show Ins. Balance $0.00 (Adjustments $228.86) | I4: Pass | J4: DEF-20 fixed
A5: RW2-04 | B5: System Administrator | C5: ARWBInhealthSA | D5: Re-sync scenarios (§5) | E5: 19510788, 19122637, 19521528, 19538684 | F5: Inspect after 16–18 Oct syncs | G5: Not-posted flagged; closed claims closed | H5: All three flagged 'Adjustment Not Posted' & returned; 19538684 → Closed – Fully Adjusted with audit | I5: Pass
A6: RW2-05 | B6: AR Agent | C6: ARAgent1 | D6: Scope & permissions (FR-ACC-05) | E6: — | F6: Probe claims / NC / other claim / assign | G6: Own claims only | H6: 23 claims; NC 0; other 404; assign 403 | I6: Pass
A7: RW2-06 | B7: AR Agent | C7: ARAgent1 | D7: Mark approved write-off as posted (§8.3) | E7: 19521528 | F7: Mark as Posted | G7: Allowed | H7: API 200 '1 claim(s) marked as posted' | I7: Pass | J7: DEF-17 fixed
A8: RW2-07 | B8: AR Agent | C8: ARAgent1 | D8: Re-sync notification to agent (§5) | E8: 19521528 | F8: Read notifications | G8: AdjustmentNotPosted | H8: Notification received | I8: Pass
A9: RW2-08 | B9: AR Agent | C9: ARAgent1 | D9: Follow-up with attachment (§8.2) | E9: 19514348 | F9: Attach 16 MB + PDF; save without category; fix | G9: Category required; 16 MB rejected; save | H9: 'choose a document category'; 'larger than 15 MB'; saved with 1 document | I9: Pass | J9: DEF-13 fixed
A10: RW2-09 | B10: AR Agent | C10: ARAgent1 | D10: Notes → QA (resubmit, write-off, 2 CIPs) | E10: 19510576, 19518771, 19521746, 19375256 | F10: Log notes | G10: Submitted for QA; CIP after QA | H10: All routed to QA | I10: Pass
A11: RW2-10 | B11: AR Agent | C11: ARAgent1 | D11: Escalate / Reassignment with reason (§8.4) | E11: 19085340, 19052061 | F11: Submit without then with reason | G11: Reason mandatory; claim stays | H11: 'Choose a reason.'; both raised; claim stays Assigned | I11: Pass
A12: RW2-11 | B12: AR Agent | C12: ARAgent1 | D12: My Work tiles (FR-MW-02) | E12: — | F12: Review tiles | G12: Incl. Pending Posting & New Denials | H12: Two new tiles missing | I12: Partial | J12: DEF-26
A13: RW2-12 | B13: QA Reviewer | C13: QA1 | D13: QA data scope (§3.2, NFR-01) | E13: — | F13: Probe claims / NC API | G13: No restricted queues | H13: 7,416 open priority claims; NC 0 | I13: Pass | J13: DEF-16 fixed
A14: RW2-13 | B14: QA Reviewer | C14: QA1 | D14: Reject requires note → same agent | E14: 19510576 | F14: Reject without / with note | G14: Note required; QA Rejected | H14: 'Add a note…'; returned to ARAgent1 | I14: Pass
A15: RW2-14 | B15: QA Reviewer | C15: QA1 | D15: Approve with attachment visible in Vault | E15: 19514348 | F15: Approve; open Document Vault | G15: Completed; doc listed | H15: Completed; 'UAT_appeal_letter…' category Appeal | I15: Pass
A16: RW2-15 | B16: QA Reviewer | C16: QA1 | D16: Bulk approve summary (FR-QA-06) | E16: 19518771, 19521746, 19375256 | F16: Approve Selected | G16: Counts CIP / write-off | H16: '2 … CIP … 1 … Write Offs'; toast '3 approved · 2 CIP … · 1 write-off' | I16: Pass
A17: RW2-16 | B17: Team Lead | C17: TeamLead | D17: Self-approval block (FR-QA-03) | E17: 19146652 | F17: Log own note; try approve UI & API | G17: Blocked | H17: Row shows Review only; API 409; checkbox still shown | I17: Partial | J17: DEF-30
A18: RW2-17 | B18: Team Lead | C18: TeamLead | D18: CIP approval single & bulk (§9.1) | E18: 19521746, 19375256 | F18: Approve & Send; Bulk Approve | G18: Sent to Client | H18: 'CIP-000004 approved'; '1 sent to the client.' | I18: Pass
A19: RW2-18 | B19: Team Lead | C19: TeamLead | D19: Bulk resolve escalation (FR-REQ-05) | E19: 19085340 | F19: Resolve Selected without / with note | G19: Note required | H19: 'Add a response note…'; '1 request resolved.' | I19: Pass
A20: RW2-19 | B20: Team Lead | C20: TeamLead | D20: Reassign & Resolve | E20: 19052061 | F20: Respond → Reassign & Resolve → ARAgent3 | G20: Reassigned; request resolved | H20: Done; 'Resolved by reassigning to ARAgent3.' | I20: Pass
A21: RW2-20 | B21: Team Lead | C21: TeamLead | D21: Auto-adjust & access | E21: 19492367 | F21: Process; probe masters / audit | G21: Allowed; masters & audit blocked | H21: Processed $4.66; masters 403; audit 403; NC 248 visible | I21: Pass
A22: RW2-21 | B22: Clinic Viewer | C22: ClinicViewer (Insight Family Practice) | D22: No internal notes (§9.2) | E22: 19521746, 19524452 | F22: Open claim page & API | G22: Hidden | H22: Tabs Overview/CPT/Denial/Documents only; API clean | I22: Pass | J22: DEF-15 fixed
A23: RW2-22 | B23: Clinic Viewer | C23: ClinicViewer (Insight Family Practice) | D23: Scope (§10.1) | E23: 19375256 | F23: Open other-clinic claim; count data | G23: Own clinic only | H23: 404; 7,300 claims | I23: Pass
A24: RW2-23 | B24: Clinic Viewer | C24: ClinicViewer (Insight Family Practice) | D24: Respond with attachment (§9.1) | E24: 19521746 | F24: 16 MB then PDF + text | G24: Respond allowed | H24: 16 MB rejected; 'Response submitted… 1 attachment(s)' | I24: Pass | J24: DEF-18 fixed
A25: RW2-24 | B25: RCM Manager | C25: RCMManager | D25: Maintain NC / Auto-Adjust lists (§10) | E25: — | F25: Open Workbench Lists | G25: Allowed | H25: NC + Auto-Adjust lists editable; API 200 | I25: Pass | J25: DEF-08 fixed
A26: RW2-25 | B26: RCM Manager | C26: RCMManager | D26: Queue after client response (§3.1) | E26: 19521746 | F26: Inspect claim | G26: CIP Response Received | H26: cipresponse | I26: Pass | J26: DEF-19 fixed
A27: RW2-26 | B27: RCM Manager | C27: RCMManager | D27: Insufficient → Round 2 | E27: 19521746 | F27: Review Response › Insufficient | G27: Re-sent with note | H27: 'marked insufficient - re-sent… (next round)' | I27: Pass
A28: RW2-27 | B28: RCM Manager | C28: RCMManager | D28: Status Change Verification | E28: 19580937 | F28: Select › Complete | G28: Closed | H28: Completed → Closed – Fully Adjusted | I28: Pass | J28: OBS-20
A29: RW2-28 | B29: Client Viewer | C29: AccountManager | D29: Round-2 and new responses | E29: 19521746, 19375256 | F29: Respond with PDFs | G29: Accepted | H29: Both submitted with attachments; Round 2 feedback shown | I29: Pass
A30: RW2-29 | B30: Client Viewer | C30: AccountManager | D30: Reports export / Work Queue (FR-RPT-04, FR-XL-03) | E30: — | F30: Open Reports, Work Queue | G30: Reports export; line-item export | H30: Reports export OK; no line-item export | I30: Partial | J30: DEF-29
A31: RW2-30 | B31: RCM Manager | C31: RCMManager | D31: Approve & Return to Agent (AT-13) | E31: 19521746, 19375256 | F31: Review Response › Approve & Return | G31: Back to ARAgent1 | H31: Both Assigned to ARAgent1, queue CIP Response Received | I31: Pass
A32: RW2-31 | B32: RCM Manager | C32: RCMManager | D32: Manager auto-adjust (FR-ADJ-02) | E32: 19491057 | F32: Process | G32: Allowed | H32: '1 claim(s) totaling $4.66 …' | I32: Pass

Sheet Defect Log
A1: Defect ID | B1: Linked Test / Req | C1: Area | D1: Severity | E1: Description | F1: Status 15 Oct | G1: Retest Status 19 Oct | H1: Retest Note
A2: DEF-01 | B2: TC-004 | C2: Dashboard | D2: High | E2: Dashboard insights panel does not show the current week's uploaded Key Observations; shows system-generated top-5 list instead (216, 252, 31, 27, 96) while Data Processing current week shows only CO-216. | F2: Open | G2: Fixed | H2: Verified in 19 Oct retest.
A3: DEF-02 | B3: TC-004, TC-005 | C3: Dashboard / Data Processing | D3: Medium | E3: Denial code Description shows '—' on Dashboard and on system-generated insight rows although the Denial Code Master holds descriptions (e.g., 216). | F3: Open | G3: Fixed | H3: Verified in 19 Oct retest.
A4: DEF-03 | B4: TC-009 | C4: Claim Detail > Denial Info | D4: Medium | E4: Denial Reason and 'All Denial Codes' empty for claim with curated 'CO11, CO252'; 'Line-Level Codes' renders '11252' (codes concatenated without separator). | F4: Open | G4: Fixed | H4: Verified in 19 Oct retest.
A5: DEF-04 | B5: TC-010 | C5: Claim Detail > CPT / Line Detail | D5: Low | E5: No per-CPT expand control; line denial sub-row lacks description and classification (only on Denial Info tab). | F5: Open | G5: Fixed | H5: Verified in 19 Oct retest.
A6: DEF-05 | B6: TC-021 | C6: Work Queue feed | D6: High | E6: Work-queue feed / nav badge (9,054) includes Non-Collectible (759) and Unbilled (1,102) claims; spec limits auto-feed to the 4 Possible Collectible queues (7,193). | F6: Open | G6: Fixed | H6: Verified in 19 Oct retest.
A7: DEF-06 | B7: TC-021 | C7: Dashboard KPI | D7: High | E7: 'Claims Awaiting Assignment' (83,986) counts every unassigned claim incl. Closed and Patient AR; should count only open Possible Collectible claims. | F7: Open | G7: Fixed | H7: Verified in 19 Oct retest.
A8: DEF-07 | B8: TC-022 | C8: Configuration | D8: High | E8: Two conflicting Non-Collectible sources: Workbench list (197, 242, 257, 288, 27, 31) vs Denial Code Master flags (29, 119, 193, 197, 204, 242, 243, 279). Queue engine uses Workbench list; 204/29 etc. treated as collectible. | F8: Open | G8: Fixed | H8: Queues use one NC list correctly (284 claims validated 20 Oct: 24/24 Non-Collectible, incl. 19460085 & 19385515). Residual: code 284 has no row in the Denial Code Master — tracked as OBS-28, not a classification defect.
A9: DEF-08 | B9: TC-023, TC-064 | C9: Roles & Access | D9: Medium | E9: RCM Manager cannot maintain NC / Auto-Adjust lists — Master Values is admin-only. | F9: Open | G9: Fixed | H9: Verified in 19 Oct retest.
A10: DEF-09 | B10: TC-031 | C10: Denial categorization | D10: High | E10: 50 primary denial codes unmapped (incl. 216 – 1,708 claims / $594.6K); 48% of denied claims categorised 'Other'. Dependent on open item #2. | F10: Open – dependency | G10: Fixed | H10: 1 unmapped code remains (CO17, 2 claims).
A11: DEF-10 | B11: TC-041 | C11: Work Queue grid | D11: Low | E11: Column header still 'Expected Payment'; should read 'Revenue Expectation'. | F11: Open | G11: Fixed | H11: Verified in 19 Oct retest.
A12: DEF-11 | B12: TC-042, TC-043, TC-044 | C12: Financial fields | D12: High | E12: Revenue Expectation = $0 on all claims (no fee schedule loaded) so Potential Recovery / Recovery Status cannot work; dashboard 'revenue expectation' uses Initial Insurance AR instead. Dependent on open item #5. | F12: Open – dependency | G12: Fixed | H12: Revenue Expectation now calculated (line-inclusion rule clarified — see OBS-27).
... A32: DEF-31 | B32: FR-CM-03 | C32: Client Management | D32: Low | E32: Per-client configuration (SharePoint source folder, onboarding status, primary account manager) not on client card. | F32: — | G32: New | H32: Found in 19 Oct retest (v1.1 scope).

Sheet Observations
A1: Obs ID | B1: Linked | C1: Observation / Clarification Needed | D1: Status 19 Oct
A2: OBS-01 | B2: TC-001 | C2: Data Processing header 'Master File Loaded' shows '—' even though run #3 loaded a file. | D2: Resolved
A3: OBS-02 | B3: TC-006 | C3: Insight count (1,699) uses primary denial only; routed Work Queue filter returns 1,700 (includes a claim with 216 as secondary code). Align filter with insight basis. | D3: Open / to confirm
A4: OBS-03 | B4: TC-014 | C4: 2 Non-Responder claims have source status 'Patient Responsibility' — confirm intended. | D4: Open / to confirm
A5: OBS-04 | B5: TC-015 | C5: 100 Denied – Possible Collectible claims carry an NC/terminal code (e.g., 242) as a secondary code in the curated column; will move once Phase 2 hierarchy is delivered. | D5: Open / to confirm
A6: OBS-05 | B6: TC-019 | C6: No Patient AR claim retains a denial code, so 'denial present → still Patient AR' could not be exercised. | D6: Open / to confirm
A7: OBS-06 | B7: TC-020, TC-033 | C7: Extra queues not in spec: 'Unbilled (Not Yet Billed)' and 'Status Change Verification'. Confirm with business owner and add to the requirement doc. | D7: Open / to confirm
A8: OBS-07 | B8: TC-025 | C8: Claims API returns AssignedAgentName = null while AssignedAgentUser is populated (display name gap). | D8: Open / to confirm
A9: OBS-08 | B9: TC-029 | C9: 'CR' (Corrections & Reversals) group prefix not stripped — CR96 falls to Unmapped/'Other'. Spec lists CO/PR/PI/OA only; confirm whether CR should be added. | D9: Resolved
A10: OBS-09 | B10: TC-035 | C10: Assignment page '6,066 claims untouched for 45+ days' counts never-worked claims; ensure this is not confused with the Re-Follow-Up – Unresolved rule (touched claims only). | D10: Open / to confirm
A11: OBS-10 | B11: TC-037 | C11: 7 Closed claims remain 'Assigned' — confirm they were assigned intentionally (special project) rather than left assigned after closing on sync. | D11: Open / to confirm
A12: OBS-11 | B12: TC-040 | C12: No dedicated 'Export Auto Adjustments report' for PMS posting; relies on generic export. | D12: Resolved (background export)
... A25: OBS-24 | B25: Document Vault | C25: Document Vault is visible to Client / Clinic Viewers (scoped to their CIP files); §16 lists it for internal roles only — confirm. | D25: New

Sheet Mockup Comparison
A1: Ref | B1: Area | C1: Mockup (Demo Account HTML) | D1: Application (Test, 19 Oct) | E1: Assessment
A2: M-01 | B2: Navigation / screens | C2: 16 screens incl. My Work, System Settings, Client Escalation Requests (viewer) | D2: All screens present; 'System Settings' replaced by 'Master Values' (9 sub-pages); adds 'Status Change Verification' | E2: Aligned (with additions)
A3: M-02 | B3: Personas / roles | C3: Admin, RCM Manager, Team Lead, AR Agent, QA Reviewer, Client Viewer (client / clinic / provider scopes) | D3: Same 8 roles incl. Clinic Viewer and Provider Viewer | E3: Aligned
A4: M-03 | B4: Dashboard KPI tiles | C4: 10 tiles: Eligible Claims, Outstanding Ins AR, Awaiting Assignment, In Progress, Awaiting QA, QA Rejected, Completed/Closed, Recovered, Potential Recovery, Overdue Follow-Ups | D4: Same 10 tiles | E4: Aligned (values: see DEF-06, DEF-11)
A5: M-04 | B5: Dashboard insight table | C5: Denial code, description, counts, balance, top payer, impact, observation, category, action | D5: Same columns; descriptions now populated | E5: Aligned
A6: M-05 | B6: Work Queue filters | C6: Client, payer, panel, category, status, agent, priority, aging, AR queue, TFL, search, saved views | D6: Same plus Clinic, Open Ins AR only, Non-collectible only | E6: Aligned
A7: M-06 | B7: Work Queue column | C7: 'Expected Payment' | D7: 'Revenue Expectation' (renamed) | E7: App follows handoff
A8: M-07 | B8: Claim detail financials | C8: Expected Payment, Potential Recovery | D8: Revenue Expectation, Potential Recovery, Recovery Status | E8: App follows handoff (better than mockup)
A9: M-08 | B9: Process Automatic Adjustments | C9: Button in restricted Work Queue; claims moved to Completed | D9: Button present; Auto Adjustments queue created (per handoff) | E9: App follows handoff
A10: M-09 | B10: Log Follow-Up Note | C10: Claim Type, Follow-Up Type, Claim Status, Root Cause, Fix/Resolution, Comment, Next Follow-Up | D10: Same fields + CIP fields + categorised attachments | E10: Aligned (exceeds mockup)
A11: M-10 | B11: CIP Escalations | C11: Review, bulk approve / reject, return to agent, re-escalate | D11: Same lifecycle and bulk actions | E11: Aligned
A12: M-11 | B12: Escalation & Reassignment Requests | C12: Screen for Admin/Mgr/TL with Mark Resolved | D12: Same; reassigning resolves request | E12: Aligned
... A16: M-15 | B16: Document Vault | C16: Not in mockup | D16: Document Vault built (search by claim / patient / category / source / date) | E16: App follows handoff

Sheet Queue Reconciliation
A1: Queue reconciliation – 84,494 claims (API pull 19 Oct 2026, before role-workflow actions)
A3: Queue | B3: Sub-queue | C3: Claims | D3: Unassigned | E3: Auto-fed per spec?
A4: Closed | B4: Fully Paid | C4: 43003 | D4: 43003 | E4: No
A5: Closed | B5: Fully Adjusted | C5: 21408 | D5: 21398 | E5: No
A6: Patient AR | B6: — | C6: 11561 | D6: 11561 | E6: No
A7: Non-Responder | B7: Possible Collectible | C7: 1715 | D7: 1710 | E7: Yes
A8: Denied | B8: Possible Collectible | C8: 5245 | D8: 5199 | E8: Yes
A9: Denied | B9: Non-Collectible | C9: 249 | D9: 249 | E9: No
A10: Partially Paid | B10: Possible Collectible | C10: 268 | D10: 256 | E10: Yes
A11: Partially Paid | B11: Non-Collectible | C11: 2 | D11: 2 | E11: No
A12: Partially Adjusted | B12: Possible Collectible | C12: 53 | D12: 53 | E12: Yes
A13: Unbilled (not in spec) | B13: — | C13: 841 | D13: 841 | E13: Not defined
A14: Auto Adjustments | B14: System Auto-Adjusted | C14: 127 | D14: 127 | E14: No
A15: Auto Adjustments | B15: Approved Write-Offs – Pending Posting | C15: 1 | D15: 0 | E15: No
... A20: Completed Claims | B20: — | C20: 3 | D20: 0 | E20: No
A21: Total | C21: =SUM(C4:C20) -> 84494 | D21: =SUM(D4:D20) -> 84399
A23: Unassigned in spec auto-fed queues | D23: =SUMIFS(D4:D20,E4:E20,"Yes") -> 7218
A24: Work Queue badge / Dashboard 'Awaiting Assignment' (observed) | D24: 7218
A25: Variance | D25: =D24-D23 -> 0
A26: Blue value read from the app UI on 19 Oct 2026; 15 Oct the badge was 9,054 vs 7,193 (variance 1,861).
